{
  "image": "/home/ubuntuuser/code/pilotless_poses/testdata/val2017/000000468501.jpg",
  "people": [
    {
      "id": 0,
      "keypoints": [
        {
          "name": "nose",
          "x": 199.42446899414062,
          "y": 102.001708984375,
          "confidence": 1.0053104162216187
        },
        {
          "name": "left_eye",
          "x": 204.50027465820312,
          "y": 98.4866943359375,
          "confidence": 1.006955623626709
        },
        {
          "name": "right_eye",
          "x": 201.07327270507812,
          "y": 97.37715148925781,
          "confidence": 0.9764402508735657
        },
        {
          "name": "left_ear",
          "x": 217.04144287109375,
          "y": 101.70292663574219,
          "confidence": 0.9472568035125732
        },
        {
          "name": "right_ear",
          "x": 218.23733520507812,
          "y": 100.38655090332031,
          "confidence": 0.7172139883041382
        },
        {
          "name": "left_shoulder",
          "x": 213.06857299804688,
          "y": 125.62939453125,
          "confidence": 0.8514242768287659
        },
        {
          "name": "right_shoulder",
          "x": 226.72335815429688,
          "y": 121.49212646484375,
          "confidence": 0.8158619999885559
        },
        {
          "name": "left_elbow",
          "x": 183.73452758789062,
          "y": 153.7091064453125,
          "confidence": 0.9679087400436401
        },
        {
          "name": "right_elbow",
          "x": 193.84042358398438,
          "y": 150.64031982421875,
          "confidence": 0.2718178629875183
        },
        {
          "name": "left_wrist",
          "x": 147.72076416015625,
          "y": 157.19473266601562,
          "confidence": 0.972098708152771
        },
        {
          "name": "right_wrist",
          "x": 241.54806518554688,
          "y": 89.97293090820312,
          "confidence": 0.327604740858078
        },
        {
          "name": "left_hip",
          "x": 220.72177124023438,
          "y": 202.99053955078125,
          "confidence": 0.9086438417434692
        },
        {
          "name": "right_hip",
          "x": 228.35647583007812,
          "y": 197.13531494140625,
          "confidence": 0.7458921074867249
        },
        {
          "name": "left_knee",
          "x": 183.15817260742188,
          "y": 250.3531494140625,
          "confidence": 0.9247274398803711
        },
        {
          "name": "right_knee",
          "x": 223.78732299804688,
          "y": 237.87875366210938,
          "confidence": 1.0109955072402954
        },
        {
          "name": "left_ankle",
          "x": 199.30575561523438,
          "y": 303.03594970703125,
          "confidence": 0.970270037651062
        },
        {
          "name": "right_ankle",
          "x": 256.0766906738281,
          "y": 266.2916259765625,
          "confidence": 0.9844516515731812
        }
      ]
    },
    {
      "id": 1,
      "keypoints": [
        {
          "name": "nose",
          "x": 255.43817138671875,
          "y": 105.24496459960938,
          "confidence": 0.905712902545929
        },
        {
          "name": "left_eye",
          "x": 259.504150390625,
          "y": 100.81924438476562,
          "confidence": 0.9514406323432922
        },
        {
          "name": "right_eye",
          "x": 256.2734375,
          "y": 100.99639892578125,
          "confidence": 0.8456425070762634
        },
        {
          "name": "left_ear",
          "x": 270.6240234375,
          "y": 104.56689453125,
          "confidence": 0.9240154027938843
        },
        {
          "name": "right_ear",
          "x": 279.16864013671875,
          "y": 106.11355590820312,
          "confidence": 0.558938205242157
        },
        {
          "name": "left_shoulder",
          "x": 278.64849853515625,
          "y": 121.632080078125,
          "confidence": 0.8696011304855347
        },
        {
          "name": "right_shoulder",
          "x": 267.45013427734375,
          "y": 146.00729370117188,
          "confidence": 0.8254915475845337
        },
        {
          "name": "left_elbow",
          "x": 231.54656982421875,
          "y": 112.49551391601562,
          "confidence": 0.7999683618545532
        },
        {
          "name": "right_elbow",
          "x": 226.2540283203125,
          "y": 149.00711059570312,
          "confidence": 1.0368365049362183
        },
        {
          "name": "left_wrist",
          "x": 237.60101318359375,
          "y": 92.03103637695312,
          "confidence": 0.7383857369422913
        },
        {
          "name": "right_wrist",
          "x": 226.78814697265625,
          "y": 122.03375244140625,
          "confidence": 0.23778069019317627
        },
        {
          "name": "left_hip",
          "x": 301.569091796875,
          "y": 227.42984008789062,
          "confidence": 0.8112194538116455
        },
        {
          "name": "right_hip",
          "x": 292.3925476074219,
          "y": 227.35275268554688,
          "confidence": 0.6557273268699646
        },
        {
          "name": "left_knee",
          "x": 258.896728515625,
          "y": 312.5386047363281,
          "confidence": 0.9006684422492981
        },
        {
          "name": "right_knee",
          "x": 268.1437683105469,
          "y": 302.9993591308594,
          "confidence": 0.7183671593666077
        },
        {
          "name": "left_ankle",
          "x": 272.3075256347656,
          "y": 372.2168884277344,
          "confidence": 0.7910760045051575
        },
        {
          "name": "right_ankle",
          "x": 292.43487548828125,
          "y": 345.6926574707031,
          "confidence": 0.9393303990364075
        }
      ]
    },
    {
      "id": 2,
      "keypoints": [
        {
          "name": "nose",
          "x": 457.99951171875,
          "y": 145.295654296875,
          "confidence": 0.9594125151634216
        },
        {
          "name": "left_eye",
          "x": 462.6129150390625,
          "y": 141.49325561523438,
          "confidence": 0.9727252125740051
        },
        {
          "name": "right_eye",
          "x": 456.14111328125,
          "y": 141.49383544921875,
          "confidence": 1.008318543434143
        },
        {
          "name": "left_ear",
          "x": 475.43438720703125,
          "y": 144.35287475585938,
          "confidence": 0.982404887676239
        },
        {
          "name": "right_ear",
          "x": 454.2587890625,
          "y": 144.06271362304688,
          "confidence": 0.8146830797195435
        },
        {
          "name": "left_shoulder",
          "x": 484.25091552734375,
          "y": 170.20574951171875,
          "confidence": 0.877766489982605
        },
        {
          "name": "right_shoulder",
          "x": 454.33453369140625,
          "y": 166.15213012695312,
          "confidence": 0.9225612282752991
        },
        {
          "name": "left_elbow",
          "x": 496.72967529296875,
          "y": 202.05242919921875,
          "confidence": 0.9493167996406555
        },
        {
          "name": "right_elbow",
          "x": 430.76812744140625,
          "y": 188.80960083007812,
          "confidence": 1.0056815147399902
        },
        {
          "name": "left_wrist",
          "x": 470.44500732421875,
          "y": 206.82235717773438,
          "confidence": 1.0196162462234497
        },
        {
          "name": "right_wrist",
          "x": 414.49603271484375,
          "y": 183.24322509765625,
          "confidence": 0.9837866425514221
        },
        {
          "name": "left_hip",
          "x": 480.58551025390625,
          "y": 222.6123046875,
          "confidence": 0.838375449180603
        },
        {
          "name": "right_hip",
          "x": 458.88824462890625,
          "y": 214.932373046875,
          "confidence": 0.9062899947166443
        },
        {
          "name": "left_knee",
          "x": 439.614501953125,
          "y": 228.09033203125,
          "confidence": 0.9284127950668335
        },
        {
          "name": "right_knee",
          "x": 414.9746398925781,
          "y": 221.38821411132812,
          "confidence": 0.9676176309585571
        },
        {
          "name": "left_ankle",
          "x": 391.3335266113281,
          "y": 259.4578857421875,
          "confidence": 0.8146846890449524
        },
        {
          "name": "right_ankle",
          "x": 379.6583251953125,
          "y": 253.08755493164062,
          "confidence": 0.8517753481864929
        }
      ]
    }
  ],
  "image_width": 0,
  "image_height": 0
}
