{
  "image": "/home/ubuntuuser/code/pilotless_poses/testdata/val2017/000000065736.jpg",
  "people": [
    {
      "id": 0,
      "keypoints": [
        {
          "name": "nose",
          "x": 229.30140686035156,
          "y": 44.42236328125,
          "confidence": 0.9753459095954895
        },
        {
          "name": "left_eye",
          "x": 231.0832061767578,
          "y": 35.593902587890625,
          "confidence": 0.9770970344543457
        },
        {
          "name": "right_eye",
          "x": 218.13551330566406,
          "y": 41.0391845703125,
          "confidence": 0.956183135509491
        },
        {
          "name": "left_ear",
          "x": 239.0597381591797,
          "y": 37.72393798828125,
          "confidence": 0.9582424163818359
        },
        {
          "name": "right_ear",
          "x": 205.7926788330078,
          "y": 52.7239990234375,
          "confidence": 0.9432225823402405
        },
        {
          "name": "left_shoulder",
          "x": 271.56463623046875,
          "y": 67.40408325195312,
          "confidence": 0.9352116584777832
        },
        {
          "name": "right_shoulder",
          "x": 205.3973846435547,
          "y": 98.20767211914062,
          "confidence": 0.9721983671188354
        },
        {
          "name": "left_elbow",
          "x": 309.3424072265625,
          "y": 114.90557861328125,
          "confidence": 0.9777196645736694
        },
        {
          "name": "right_elbow",
          "x": 212.4345245361328,
          "y": 144.5572509765625,
          "confidence": 0.9526514410972595
        },
        {
          "name": "left_wrist",
          "x": 281.83013916015625,
          "y": 110.94015502929688,
          "confidence": 0.9911030530929565
        },
        {
          "name": "right_wrist",
          "x": 241.24998474121094,
          "y": 118.842041015625,
          "confidence": 0.9992094039916992
        },
        {
          "name": "left_hip",
          "x": 300.3641357421875,
          "y": 187.64935302734375,
          "confidence": 0.7948449850082397
        },
        {
          "name": "right_hip",
          "x": 250.0729522705078,
          "y": 198.46502685546875,
          "confidence": 0.8646247386932373
        },
        {
          "name": "left_knee",
          "x": 323.312744140625,
          "y": 282.267822265625,
          "confidence": 0.9458752274513245
        },
        {
          "name": "right_knee",
          "x": 239.8657989501953,
          "y": 284.45745849609375,
          "confidence": 0.9773269891738892
        },
        {
          "name": "left_ankle",
          "x": 347.376953125,
          "y": 358.414306640625,
          "confidence": 0.9145013689994812
        },
        {
          "name": "right_ankle",
          "x": 242.38331604003906,
          "y": 376.82257080078125,
          "confidence": 0.9074664115905762
        }
      ]
    }
  ],
  "image_width": 0,
  "image_height": 0
}
