{
  "image": "/home/ubuntuuser/code/pilotless_poses/testdata/val2017/000000103548.jpg",
  "people": [
    {
      "id": 0,
      "keypoints": [
        {
          "name": "nose",
          "x": 544.9414672851562,
          "y": 217.47361755371094,
          "confidence": 0.904836118221283
        },
        {
          "name": "left_eye",
          "x": 545.9058837890625,
          "y": 216.0622100830078,
          "confidence": 0.9156861901283264
        },
        {
          "name": "right_eye",
          "x": 545.4345703125,
          "y": 215.96971130371094,
          "confidence": 0.7431679964065552
        },
        {
          "name": "left_ear",
          "x": 548.0136108398438,
          "y": 217.31825256347656,
          "confidence": 0.9674285054206848
        },
        {
          "name": "right_ear",
          "x": 553.656982421875,
          "y": 216.9567413330078,
          "confidence": 0.861777663230896
        },
        {
          "name": "left_shoulder",
          "x": 546.6542358398438,
          "y": 226.0863494873047,
          "confidence": 0.9413881897926331
        },
        {
          "name": "right_shoulder",
          "x": 558.1594848632812,
          "y": 226.1339874267578,
          "confidence": 0.9741353392601013
        },
        {
          "name": "left_elbow",
          "x": 548.8709106445312,
          "y": 236.80348205566406,
          "confidence": 0.9555047750473022
        },
        {
          "name": "right_elbow",
          "x": 562.9549560546875,
          "y": 237.5345916748047,
          "confidence": 0.9504091143608093
        },
        {
          "name": "left_wrist",
          "x": 541.6675415039062,
          "y": 237.94541931152344,
          "confidence": 0.9673940539360046
        },
        {
          "name": "right_wrist",
          "x": 556.1400146484375,
          "y": 240.8996124267578,
          "confidence": 0.50444495677948
        },
        {
          "name": "left_hip",
          "x": 547.93310546875,
          "y": 247.87831115722656,
          "confidence": 0.7719647288322449
        },
        {
          "name": "right_hip",
          "x": 556.523681640625,
          "y": 247.7779998779297,
          "confidence": 0.8302433490753174
        },
        {
          "name": "left_knee",
          "x": 541.4043579101562,
          "y": 266.14727783203125,
          "confidence": 0.8670868277549744
        },
        {
          "name": "right_knee",
          "x": 556.2675170898438,
          "y": 268.73480224609375,
          "confidence": 0.9358185529708862
        },
        {
          "name": "left_ankle",
          "x": 545.5372924804688,
          "y": 285.3328857421875,
          "confidence": 0.8940160870552063
        },
        {
          "name": "right_ankle",
          "x": 562.8510131835938,
          "y": 286.5029296875,
          "confidence": 0.8955959677696228
        }
      ]
    }
  ],
  "image_width": 0,
  "image_height": 0
}
