{
  "image": "/home/ubuntuuser/code/pilotless_poses/testdata/val2017/000000341094.jpg",
  "people": [
    {
      "id": 0,
      "keypoints": [
        {
          "name": "nose",
          "x": 330.8144226074219,
          "y": 191.73812866210938,
          "confidence": 0.9707169532775879
        },
        {
          "name": "left_eye",
          "x": 335.2256774902344,
          "y": 186.23037719726562,
          "confidence": 0.9412840604782104
        },
        {
          "name": "right_eye",
          "x": 323.5621032714844,
          "y": 189.30865478515625,
          "confidence": 0.9678056836128235
        },
        {
          "name": "left_ear",
          "x": 344.2498474121094,
          "y": 191.60995483398438,
          "confidence": 0.9495005011558533
        },
        {
          "name": "right_ear",
          "x": 316.92022705078125,
          "y": 197.4183349609375,
          "confidence": 0.7722486257553101
        },
        {
          "name": "left_shoulder",
          "x": 363.1871337890625,
          "y": 217.04086303710938,
          "confidence": 0.3956255614757538
        },
        {
          "name": "right_shoulder",
          "x": 317.2759704589844,
          "y": 222.69973754882812,
          "confidence": 0.3532811105251312
        },
        {
          "name": "left_elbow",
          "x": 365.24102783203125,
          "y": 239.2537841796875,
          "confidence": 0.059397850185632706
        },
        {
          "name": "right_elbow",
          "x": 302.1802673339844,
          "y": 240.74868774414062,
          "confidence": 0.07325635105371475
        },
        {
          "name": "left_wrist",
          "x": 345.3182373046875,
          "y": 212.90878295898438,
          "confidence": 0.4672200381755829
        },
        {
          "name": "right_wrist",
          "x": 313.4757385253906,
          "y": 200.53509521484375,
          "confidence": 0.13575923442840576
        },
        {
          "name": "left_hip",
          "x": 373.3139343261719,
          "y": 237.86898803710938,
          "confidence": 0.01655227318406105
        },
        {
          "name": "right_hip",
          "x": 332.7761535644531,
          "y": 237.821044921875,
          "confidence": 0.006736732553690672
        },
        {
          "name": "left_knee",
          "x": 373.6001281738281,
          "y": 238.91195678710938,
          "confidence": 0.07310657948255539
        },
        {
          "name": "right_knee",
          "x": 374.0027160644531,
          "y": 237.28317260742188,
          "confidence": 0.046757783740758896
        },
        {
          "name": "left_ankle",
          "x": 347.560546875,
          "y": 221.31387329101562,
          "confidence": 0.05102815851569176
        },
        {
          "name": "right_ankle",
          "x": 332.8004150390625,
          "y": 236.95437622070312,
          "confidence": 0.04225105047225952
        }
      ]
    }
  ],
  "image_width": 0,
  "image_height": 0
}
