{
  "image": "/home/ubuntuuser/code/pilotless_poses/testdata/val2017/000000357742.jpg",
  "people": [
    {
      "id": 0,
      "keypoints": [
        {
          "name": "nose",
          "x": 194.16461181640625,
          "y": 450.78192138671875,
          "confidence": 0.6470186114311218
        },
        {
          "name": "left_eye",
          "x": 191.85833740234375,
          "y": 448.37188720703125,
          "confidence": 0.46898049116134644
        },
        {
          "name": "right_eye",
          "x": 193.98641967773438,
          "y": 448.23052978515625,
          "confidence": 0.7708702683448792
        },
        {
          "name": "left_ear",
          "x": 179.67230224609375,
          "y": 445.65625,
          "confidence": 0.9445245265960693
        },
        {
          "name": "right_ear",
          "x": 192.40921020507812,
          "y": 448.63665771484375,
          "confidence": 0.9538278579711914
        },
        {
          "name": "left_shoulder",
          "x": 165.82923889160156,
          "y": 462.4036865234375,
          "confidence": 0.886428713798523
        },
        {
          "name": "right_shoulder",
          "x": 193.16329956054688,
          "y": 465.218994140625,
          "confidence": 0.936233639717102
        },
        {
          "name": "left_elbow",
          "x": 147.4925079345703,
          "y": 473.31866455078125,
          "confidence": 1.038130760192871
        },
        {
          "name": "right_elbow",
          "x": 205.57705688476562,
          "y": 488.0125732421875,
          "confidence": 0.9495559334754944
        },
        {
          "name": "left_wrist",
          "x": 158.1836700439453,
          "y": 468.244140625,
          "confidence": 0.5827613472938538
        },
        {
          "name": "right_wrist",
          "x": 216.56045532226562,
          "y": 480.72052001953125,
          "confidence": 0.9479169845581055
        },
        {
          "name": "left_hip",
          "x": 170.31417846679688,
          "y": 513.7587280273438,
          "confidence": 0.8126411437988281
        },
        {
          "name": "right_hip",
          "x": 190.62362670898438,
          "y": 512.3118286132812,
          "confidence": 0.7844286561012268
        },
        {
          "name": "left_knee",
          "x": 168.5017547607422,
          "y": 545.6710205078125,
          "confidence": 0.8853305578231812
        },
        {
          "name": "right_knee",
          "x": 195.73049926757812,
          "y": 536.6502075195312,
          "confidence": 0.9633635878562927
        },
        {
          "name": "left_ankle",
          "x": 162.40357971191406,
          "y": 580.2332153320312,
          "confidence": 0.7382098436355591
        },
        {
          "name": "right_ankle",
          "x": 199.448974609375,
          "y": 568.6964111328125,
          "confidence": 0.8358402848243713
        }
      ]
    }
  ],
  "image_width": 0,
  "image_height": 0
}
