{
  "image": "/home/ubuntuuser/code/pilotless_poses/testdata/val2017/000000381639.jpg",
  "people": [
    {
      "id": 0,
      "keypoints": [
        {
          "name": "nose",
          "x": 216.81228637695312,
          "y": 279.38323974609375,
          "confidence": 1.0173511505126953
        },
        {
          "name": "left_eye",
          "x": 225.6112060546875,
          "y": 270.27545166015625,
          "confidence": 0.9939621686935425
        },
        {
          "name": "right_eye",
          "x": 207.4029541015625,
          "y": 273.3321533203125,
          "confidence": 0.9993835687637329
        },
        {
          "name": "left_ear",
          "x": 244.3572998046875,
          "y": 272.18536376953125,
          "confidence": 0.9872907996177673
        },
        {
          "name": "right_ear",
          "x": 199.055908203125,
          "y": 281.848876953125,
          "confidence": 0.8862789273262024
        },
        {
          "name": "left_shoulder",
          "x": 247.73199462890625,
          "y": 310.8172607421875,
          "confidence": 0.9449314475059509
        },
        {
          "name": "right_shoulder",
          "x": 208.33758544921875,
          "y": 325.97540283203125,
          "confidence": 0.9177967309951782
        },
        {
          "name": "left_elbow",
          "x": 252.5960693359375,
          "y": 344.2813720703125,
          "confidence": 0.8387873768806458
        },
        {
          "name": "right_elbow",
          "x": 197.56182861328125,
          "y": 382.6820068359375,
          "confidence": 0.926943302154541
        },
        {
          "name": "left_wrist",
          "x": 267.7330322265625,
          "y": 364.16815185546875,
          "confidence": 0.8320558667182922
        },
        {
          "name": "right_wrist",
          "x": 246.67034912109375,
          "y": 376.992431640625,
          "confidence": 0.9871864914894104
        },
        {
          "name": "left_hip",
          "x": 244.57965087890625,
          "y": 411.88189697265625,
          "confidence": 0.8550266623497009
        },
        {
          "name": "right_hip",
          "x": 213.22174072265625,
          "y": 420.1468505859375,
          "confidence": 0.8443834185600281
        },
        {
          "name": "left_knee",
          "x": 240.20855712890625,
          "y": 475.76214599609375,
          "confidence": 0.9322235584259033
        },
        {
          "name": "right_knee",
          "x": 208.97772216796875,
          "y": 486.635009765625,
          "confidence": 0.9252557158470154
        },
        {
          "name": "left_ankle",
          "x": 240.15621948242188,
          "y": 532.0947265625,
          "confidence": 0.9669292569160461
        },
        {
          "name": "right_ankle",
          "x": 215.4044189453125,
          "y": 551.4658203125,
          "confidence": 0.9626256227493286
        }
      ]
    },
    {
      "id": 1,
      "keypoints": [
        {
          "name": "nose",
          "x": 244.29537963867188,
          "y": 71.15200805664062,
          "confidence": 0.8605502843856812
        },
        {
          "name": "left_eye",
          "x": 244.34841918945312,
          "y": 69.64338684082031,
          "confidence": 0.887078583240509
        },
        {
          "name": "right_eye",
          "x": 244.0390625,
          "y": 69.71552276611328,
          "confidence": 0.8127412796020508
        },
        {
          "name": "left_ear",
          "x": 246.44992065429688,
          "y": 68.66828918457031,
          "confidence": 0.8692600131034851
        },
        {
          "name": "right_ear",
          "x": 249.72616577148438,
          "y": 68.14022827148438,
          "confidence": 0.642787754535675
        },
        {
          "name": "left_shoulder",
          "x": 248.80340576171875,
          "y": 73.89743041992188,
          "confidence": 0.8094067573547363
        },
        {
          "name": "right_shoulder",
          "x": 255.6851806640625,
          "y": 74.51268768310547,
          "confidence": 0.7852085828781128
        },
        {
          "name": "left_elbow",
          "x": 247.6143798828125,
          "y": 82.28755187988281,
          "confidence": 0.765963077545166
        },
        {
          "name": "right_elbow",
          "x": 258.7789306640625,
          "y": 84.82755279541016,
          "confidence": 0.8264644145965576
        },
        {
          "name": "left_wrist",
          "x": 240.32061767578125,
          "y": 84.73347473144531,
          "confidence": 0.8534319400787354
        },
        {
          "name": "right_wrist",
          "x": 254.57528686523438,
          "y": 88.8206558227539,
          "confidence": 0.33213159441947937
        },
        {
          "name": "left_hip",
          "x": 249.31240844726562,
          "y": 93.38697814941406,
          "confidence": 0.6337264776229858
        },
        {
          "name": "right_hip",
          "x": 256.0522766113281,
          "y": 93.22554779052734,
          "confidence": 0.5895307660102844
        },
        {
          "name": "left_knee",
          "x": 247.28860473632812,
          "y": 106.07945251464844,
          "confidence": 0.503331184387207
        },
        {
          "name": "right_knee",
          "x": 253.7542724609375,
          "y": 106.74354553222656,
          "confidence": 0.5850040912628174
        },
        {
          "name": "left_ankle",
          "x": 246.259765625,
          "y": 110.47102355957031,
          "confidence": 0.1169913113117218
        },
        {
          "name": "right_ankle",
          "x": 252.27694702148438,
          "y": 110.46286010742188,
          "confidence": 0.047438908368349075
        }
      ]
    },
    {
      "id": 2,
      "keypoints": [
        {
          "name": "nose",
          "x": 224.8860321044922,
          "y": 48.60519027709961,
          "confidence": 0.8755078315734863
        },
        {
          "name": "left_eye",
          "x": 224.954345703125,
          "y": 47.095462799072266,
          "confidence": 0.8817008137702942
        },
        {
          "name": "right_eye",
          "x": 224.1708984375,
          "y": 47.0872917175293,
          "confidence": 0.932374119758606
        },
        {
          "name": "left_ear",
          "x": 219.91412353515625,
          "y": 46.576351165771484,
          "confidence": 0.611592710018158
        },
        {
          "name": "right_ear",
          "x": 220.8468017578125,
          "y": 46.566280364990234,
          "confidence": 0.872333288192749
        },
        {
          "name": "left_shoulder",
          "x": 214.0430908203125,
          "y": 54.6281852722168,
          "confidence": 0.8161646127700806
        },
        {
          "name": "right_shoulder",
          "x": 224.55374145507812,
          "y": 54.700801849365234,
          "confidence": 0.6664315462112427
        },
        {
          "name": "left_elbow",
          "x": 211.5536346435547,
          "y": 64.71649169921875,
          "confidence": 0.7863367199897766
        },
        {
          "name": "right_elbow",
          "x": 230.8981170654297,
          "y": 65.39704895019531,
          "confidence": 0.491929829120636
        },
        {
          "name": "left_wrist",
          "x": 213.2515869140625,
          "y": 73.58799743652344,
          "confidence": 0.6941844820976257
        },
        {
          "name": "right_wrist",
          "x": 232.34596252441406,
          "y": 72.21391296386719,
          "confidence": 0.37784305214881897
        },
        {
          "name": "left_hip",
          "x": 217.4290313720703,
          "y": 73.38812255859375,
          "confidence": 0.560421884059906
        },
        {
          "name": "right_hip",
          "x": 225.18727111816406,
          "y": 73.35293579101562,
          "confidence": 0.563500165939331
        },
        {
          "name": "left_knee",
          "x": 217.8482208251953,
          "y": 83.52847290039062,
          "confidence": 0.0811329334974289
        },
        {
          "name": "right_knee",
          "x": 229.89149475097656,
          "y": 83.52684020996094,
          "confidence": 0.09497223794460297
        },
        {
          "name": "left_ankle",
          "x": 238.52145385742188,
          "y": 83.53572082519531,
          "confidence": 0.02573438361287117
        },
        {
          "name": "right_ankle",
          "x": 238.2433624267578,
          "y": 83.55352783203125,
          "confidence": 0.04597114026546478
        }
      ]
    },
    {
      "id": 3,
      "keypoints": [
        {
          "name": "nose",
          "x": 308.7489929199219,
          "y": 103.60647583007812,
          "confidence": 0.9100181460380554
        },
        {
          "name": "left_eye",
          "x": 308.7518310546875,
          "y": 102.2535400390625,
          "confidence": 0.8893221616744995
        },
        {
          "name": "right_eye",
          "x": 308.6000671386719,
          "y": 102.2266845703125,
          "confidence": 0.8023862242698669
        },
        {
          "name": "left_ear",
          "x": 310.32183837890625,
          "y": 101.88665771484375,
          "confidence": 0.9032421112060547
        },
        {
          "name": "right_ear",
          "x": 315.0196533203125,
          "y": 100.36529541015625,
          "confidence": 0.8449059724807739
        },
        {
          "name": "left_shoulder",
          "x": 312.1062927246094,
          "y": 108.49317932128906,
          "confidence": 0.9253225326538086
        },
        {
          "name": "right_shoulder",
          "x": 319.9591979980469,
          "y": 105.74276733398438,
          "confidence": 0.8745752573013306
        },
        {
          "name": "left_elbow",
          "x": 310.837646484375,
          "y": 119.90109252929688,
          "confidence": 0.8646441102027893
        },
        {
          "name": "right_elbow",
          "x": 323.95953369140625,
          "y": 115.33465576171875,
          "confidence": 0.5293638706207275
        },
        {
          "name": "left_wrist",
          "x": 307.95025634765625,
          "y": 128.95925903320312,
          "confidence": 0.9060923457145691
        },
        {
          "name": "right_wrist",
          "x": 326.8497619628906,
          "y": 124.06132507324219,
          "confidence": 0.5100279450416565
        },
        {
          "name": "left_hip",
          "x": 316.7165832519531,
          "y": 126.174560546875,
          "confidence": 0.7862633466720581
        },
        {
          "name": "right_hip",
          "x": 322.1744689941406,
          "y": 125.09140014648438,
          "confidence": 0.7412659525871277
        },
        {
          "name": "left_knee",
          "x": 316.5266418457031,
          "y": 141.74850463867188,
          "confidence": 0.7828338146209717
        },
        {
          "name": "right_knee",
          "x": 317.9173889160156,
          "y": 141.04437255859375,
          "confidence": 0.7418226003646851
        },
        {
          "name": "left_ankle",
          "x": 319.6940002441406,
          "y": 155.43898010253906,
          "confidence": 0.7766997814178467
        },
        {
          "name": "right_ankle",
          "x": 320.11578369140625,
          "y": 154.90411376953125,
          "confidence": 0.5499038696289062
        }
      ]
    },
    {
      "id": 4,
      "keypoints": [
        {
          "name": "nose",
          "x": 194.9390869140625,
          "y": 52.33531951904297,
          "confidence": 0.8670737743377686
        },
        {
          "name": "left_eye",
          "x": 195.81109619140625,
          "y": 51.05188751220703,
          "confidence": 0.8860225081443787
        },
        {
          "name": "right_eye",
          "x": 194.92837524414062,
          "y": 51.025733947753906,
          "confidence": 0.8658550381660461
        },
        {
          "name": "left_ear",
          "x": 198.77883911132812,
          "y": 50.99523162841797,
          "confidence": 0.6121826171875
        },
        {
          "name": "right_ear",
          "x": 200.501953125,
          "y": 50.80781555175781,
          "confidence": 0.6756687164306641
        },
        {
          "name": "left_shoulder",
          "x": 197.07174682617188,
          "y": 57.49591064453125,
          "confidence": 0.7429500222206116
        },
        {
          "name": "right_shoulder",
          "x": 205.4151611328125,
          "y": 57.303016662597656,
          "confidence": 0.7357509136199951
        },
        {
          "name": "left_elbow",
          "x": 196.50888061523438,
          "y": 66.75548553466797,
          "confidence": 0.5780153870582581
        },
        {
          "name": "right_elbow",
          "x": 206.69903564453125,
          "y": 67.43368530273438,
          "confidence": 0.5905210971832275
        },
        {
          "name": "left_wrist",
          "x": 196.55886840820312,
          "y": 71.80455017089844,
          "confidence": 0.3374617397785187
        },
        {
          "name": "right_wrist",
          "x": 205.62594604492188,
          "y": 72.19864654541016,
          "confidence": 0.3452748954296112
        },
        {
          "name": "left_hip",
          "x": 199.2442626953125,
          "y": 74.2546615600586,
          "confidence": 0.42451339960098267
        },
        {
          "name": "right_hip",
          "x": 204.98593139648438,
          "y": 74.16089630126953,
          "confidence": 0.4756372570991516
        },
        {
          "name": "left_knee",
          "x": 187.9097900390625,
          "y": 76.40099334716797,
          "confidence": 0.0200177188962698
        },
        {
          "name": "right_knee",
          "x": 210.28558349609375,
          "y": 77.1486587524414,
          "confidence": 0.011417264118790627
        },
        {
          "name": "left_ankle",
          "x": 198.94540405273438,
          "y": 76.71198272705078,
          "confidence": 0.06541528552770615
        },
        {
          "name": "right_ankle",
          "x": 203.75296020507812,
          "y": 76.74494934082031,
          "confidence": 0.028865614905953407
        }
      ]
    },
    {
      "id": 5,
      "keypoints": [
        {
          "name": "nose",
          "x": 271.89605712890625,
          "y": 98.43526458740234,
          "confidence": 0.7708364129066467
        },
        {
          "name": "left_eye",
          "x": 272.1722106933594,
          "y": 97.29863739013672,
          "confidence": 0.8038214445114136
        },
        {
          "name": "right_eye",
          "x": 272.333740234375,
          "y": 97.1899642944336,
          "confidence": 0.6173467636108398
        },
        {
          "name": "left_ear",
          "x": 272.8333435058594,
          "y": 97.97870635986328,
          "confidence": 0.8295116424560547
        },
        {
          "name": "right_ear",
          "x": 278.79730224609375,
          "y": 96.89861297607422,
          "confidence": 0.844977617263794
        },
        {
          "name": "left_shoulder",
          "x": 273.2386779785156,
          "y": 105.23546600341797,
          "confidence": 0.9412176012992859
        },
        {
          "name": "right_shoulder",
          "x": 283.12750244140625,
          "y": 104.40428924560547,
          "confidence": 0.9178861379623413
        },
        {
          "name": "left_elbow",
          "x": 272.5229797363281,
          "y": 112.7605972290039,
          "confidence": 0.6743992567062378
        },
        {
          "name": "right_elbow",
          "x": 286.6456298828125,
          "y": 111.41976165771484,
          "confidence": 0.8390589356422424
        },
        {
          "name": "left_wrist",
          "x": 273.9870300292969,
          "y": 117.64444732666016,
          "confidence": 0.5725625157356262
        },
        {
          "name": "right_wrist",
          "x": 284.6369323730469,
          "y": 117.4780502319336,
          "confidence": 0.7129944562911987
        },
        {
          "name": "left_hip",
          "x": 277.7373352050781,
          "y": 120.38378143310547,
          "confidence": 0.7119960784912109
        },
        {
          "name": "right_hip",
          "x": 284.5472106933594,
          "y": 119.76726531982422,
          "confidence": 0.6630497574806213
        },
        {
          "name": "left_knee",
          "x": 280.32391357421875,
          "y": 130.69171142578125,
          "confidence": 0.5987597107887268
        },
        {
          "name": "right_knee",
          "x": 287.98907470703125,
          "y": 130.53857421875,
          "confidence": 0.6539942622184753
        },
        {
          "name": "left_ankle",
          "x": 280.4203796386719,
          "y": 141.08319091796875,
          "confidence": 0.5534986257553101
        },
        {
          "name": "right_ankle",
          "x": 288.2558288574219,
          "y": 140.50686645507812,
          "confidence": 0.5810917019844055
        }
      ]
    },
    {
      "id": 6,
      "keypoints": [
        {
          "name": "nose",
          "x": 472.7495422363281,
          "y": 96.69383239746094,
          "confidence": 0.9209313988685608
        },
        {
          "name": "left_eye",
          "x": 474.2398376464844,
          "y": 94.96073913574219,
          "confidence": 0.9674010872840881
        },
        {
          "name": "right_eye",
          "x": 471.6537170410156,
          "y": 95.19267272949219,
          "confidence": 0.9358784556388855
        },
        {
          "name": "left_ear",
          "x": 477.1167297363281,
          "y": 95.57196044921875,
          "confidence": 0.897082507610321
        },
        {
          "name": "right_ear",
          "x": 470.2607421875,
          "y": 96.27481079101562,
          "confidence": 0.8515374660491943
        },
        {
          "name": "left_shoulder",
          "x": 481.79510498046875,
          "y": 102.99525451660156,
          "confidence": 0.8245759606361389
        },
        {
          "name": "right_shoulder",
          "x": 469.45526123046875,
          "y": 104.70246887207031,
          "confidence": 0.9394261837005615
        },
        {
          "name": "left_elbow",
          "x": 485.0245361328125,
          "y": 113.66802978515625,
          "confidence": 0.6096265912055969
        },
        {
          "name": "right_elbow",
          "x": 465.3668212890625,
          "y": 114.72602844238281,
          "confidence": 0.8317555785179138
        },
        {
          "name": "left_wrist",
          "x": 477.1192626953125,
          "y": 119.22390747070312,
          "confidence": 0.6881390810012817
        },
        {
          "name": "right_wrist",
          "x": 467.49737548828125,
          "y": 121.51356506347656,
          "confidence": 0.7551631927490234
        },
        {
          "name": "left_hip",
          "x": 479.66070556640625,
          "y": 125.99076843261719,
          "confidence": 0.7144537568092346
        },
        {
          "name": "right_hip",
          "x": 470.82806396484375,
          "y": 125.5980224609375,
          "confidence": 0.7512606978416443
        },
        {
          "name": "left_knee",
          "x": 478.0614929199219,
          "y": 141.7305145263672,
          "confidence": 0.5224143862724304
        },
        {
          "name": "right_knee",
          "x": 468.8839416503906,
          "y": 140.80027770996094,
          "confidence": 0.5542930364608765
        },
        {
          "name": "left_ankle",
          "x": 477.130615234375,
          "y": 155.49642944335938,
          "confidence": 0.48530158400535583
        },
        {
          "name": "right_ankle",
          "x": 467.1829833984375,
          "y": 153.62294006347656,
          "confidence": 0.6641497015953064
        }
      ]
    },
    {
      "id": 7,
      "keypoints": [
        {
          "name": "nose",
          "x": 337.7508239746094,
          "y": 108.44723510742188,
          "confidence": 0.9739604592323303
        },
        {
          "name": "left_eye",
          "x": 337.4814758300781,
          "y": 106.87286376953125,
          "confidence": 0.9514673948287964
        },
        {
          "name": "right_eye",
          "x": 337.1511535644531,
          "y": 107.175537109375,
          "confidence": 0.9324594736099243
        },
        {
          "name": "left_ear",
          "x": 338.8084411621094,
          "y": 104.68843078613281,
          "confidence": 0.8738442659378052
        },
        {
          "name": "right_ear",
          "x": 340.351806640625,
          "y": 103.159423828125,
          "confidence": 0.6094579696655273
        },
        {
          "name": "left_shoulder",
          "x": 343.7150573730469,
          "y": 108.53910827636719,
          "confidence": 0.9739566445350647
        },
        {
          "name": "right_shoulder",
          "x": 347.5338439941406,
          "y": 105.53935241699219,
          "confidence": 0.7629550695419312
        },
        {
          "name": "left_elbow",
          "x": 346.5316467285156,
          "y": 118.97731018066406,
          "confidence": 0.9053190350532532
        },
        {
          "name": "right_elbow",
          "x": 349.6923828125,
          "y": 116.74662780761719,
          "confidence": 0.4555566906929016
        },
        {
          "name": "left_wrist",
          "x": 345.64715576171875,
          "y": 130.4022674560547,
          "confidence": 0.8787837028503418
        },
        {
          "name": "right_wrist",
          "x": 340.8481750488281,
          "y": 117.66522216796875,
          "confidence": 0.314139723777771
        },
        {
          "name": "left_hip",
          "x": 348.03558349609375,
          "y": 126.06976318359375,
          "confidence": 0.6019262671470642
        },
        {
          "name": "right_hip",
          "x": 352.03326416015625,
          "y": 124.32984924316406,
          "confidence": 0.599101722240448
        },
        {
          "name": "left_knee",
          "x": 347.2904357910156,
          "y": 141.88038635253906,
          "confidence": 0.5534173250198364
        },
        {
          "name": "right_knee",
          "x": 350.69647216796875,
          "y": 141.86322021484375,
          "confidence": 0.6606245040893555
        },
        {
          "name": "left_ankle",
          "x": 347.5557861328125,
          "y": 157.2585906982422,
          "confidence": 0.5689635872840881
        },
        {
          "name": "right_ankle",
          "x": 349.5975341796875,
          "y": 156.87399291992188,
          "confidence": 0.6427502632141113
        }
      ]
    },
    {
      "id": 8,
      "keypoints": [
        {
          "name": "nose",
          "x": 501.6279602050781,
          "y": 91.3697509765625,
          "confidence": 0.5365121960639954
        },
        {
          "name": "left_eye",
          "x": 501.1369323730469,
          "y": 90.42511749267578,
          "confidence": 0.27389734983444214
        },
        {
          "name": "right_eye",
          "x": 501.6796569824219,
          "y": 90.05852508544922,
          "confidence": 0.5848953127861023
        },
        {
          "name": "left_ear",
          "x": 495.5646057128906,
          "y": 89.84671783447266,
          "confidence": 0.7567456960678101
        },
        {
          "name": "right_ear",
          "x": 501.3412780761719,
          "y": 90.14778900146484,
          "confidence": 0.7610670924186707
        },
        {
          "name": "left_shoulder",
          "x": 489.0217590332031,
          "y": 95.9720458984375,
          "confidence": 0.7979746460914612
        },
        {
          "name": "right_shoulder",
          "x": 503.3590393066406,
          "y": 96.20104217529297,
          "confidence": 0.871350109577179
        },
        {
          "name": "left_elbow",
          "x": 486.4522399902344,
          "y": 106.18424224853516,
          "confidence": 0.6706153154373169
        },
        {
          "name": "right_elbow",
          "x": 505.5430603027344,
          "y": 105.4992904663086,
          "confidence": 0.6603912711143494
        },
        {
          "name": "left_wrist",
          "x": 487.398681640625,
          "y": 113.33177947998047,
          "confidence": 0.43508002161979675
        },
        {
          "name": "right_wrist",
          "x": 504.1060485839844,
          "y": 111.20890045166016,
          "confidence": 0.2948782742023468
        },
        {
          "name": "left_hip",
          "x": 492.8126525878906,
          "y": 116.31835174560547,
          "confidence": 0.370961993932724
        },
        {
          "name": "right_hip",
          "x": 503.0094909667969,
          "y": 116.54615020751953,
          "confidence": 0.3968641459941864
        },
        {
          "name": "left_knee",
          "x": 491.6329650878906,
          "y": 133.75672912597656,
          "confidence": 0.18869255483150482
        },
        {
          "name": "right_knee",
          "x": 501.3698425292969,
          "y": 126.05399322509766,
          "confidence": 0.15444058179855347
        },
        {
          "name": "left_ankle",
          "x": 489.41632080078125,
          "y": 133.73941040039062,
          "confidence": 0.21611624956130981
        },
        {
          "name": "right_ankle",
          "x": 502.6086730957031,
          "y": 129.19424438476562,
          "confidence": 0.36635100841522217
        }
      ]
    },
    {
      "id": 9,
      "keypoints": [
        {
          "name": "nose",
          "x": 499.747314453125,
          "y": 91.68949890136719,
          "confidence": 0.6888065934181213
        },
        {
          "name": "left_eye",
          "x": 499.98773193359375,
          "y": 90.41120910644531,
          "confidence": 0.6422384977340698
        },
        {
          "name": "right_eye",
          "x": 500.02142333984375,
          "y": 90.19371032714844,
          "confidence": 0.7244073152542114
        },
        {
          "name": "left_ear",
          "x": 495.4544677734375,
          "y": 89.05720520019531,
          "confidence": 0.8211828470230103
        },
        {
          "name": "right_ear",
          "x": 501.03314208984375,
          "y": 89.89718627929688,
          "confidence": 0.8071132898330688
        },
        {
          "name": "left_shoulder",
          "x": 489.37542724609375,
          "y": 96.07695007324219,
          "confidence": 0.8673311471939087
        },
        {
          "name": "right_shoulder",
          "x": 503.52880859375,
          "y": 96.55892944335938,
          "confidence": 0.9137846231460571
        },
        {
          "name": "left_elbow",
          "x": 486.95135498046875,
          "y": 106.41781616210938,
          "confidence": 0.8077734708786011
        },
        {
          "name": "right_elbow",
          "x": 505.6376953125,
          "y": 106.66070556640625,
          "confidence": 0.7996479272842407
        },
        {
          "name": "left_wrist",
          "x": 487.05438232421875,
          "y": 113.55899047851562,
          "confidence": 0.6097213625907898
        },
        {
          "name": "right_wrist",
          "x": 504.2298583984375,
          "y": 112.39109802246094,
          "confidence": 0.46665412187576294
        },
        {
          "name": "left_hip",
          "x": 492.96417236328125,
          "y": 116.80308532714844,
          "confidence": 0.6979174613952637
        },
        {
          "name": "right_hip",
          "x": 502.7718505859375,
          "y": 116.91416931152344,
          "confidence": 0.6537696123123169
        },
        {
          "name": "left_knee",
          "x": 492.0081787109375,
          "y": 134.12261962890625,
          "confidence": 0.7180803418159485
        },
        {
          "name": "right_knee",
          "x": 499.00238037109375,
          "y": 133.82334899902344,
          "confidence": 0.5887615084648132
        },
        {
          "name": "left_ankle",
          "x": 493.39874267578125,
          "y": 149.9804229736328,
          "confidence": 0.6878891587257385
        },
        {
          "name": "right_ankle",
          "x": 496.8184814453125,
          "y": 148.68284606933594,
          "confidence": 0.5715481042861938
        }
      ]
    },
    {
      "id": 10,
      "keypoints": [
        {
          "name": "nose",
          "x": 379.4643859863281,
          "y": 129.944580078125,
          "confidence": 0.31738513708114624
        },
        {
          "name": "left_eye",
          "x": 380.8691711425781,
          "y": 129.277587890625,
          "confidence": 0.34579548239707947
        },
        {
          "name": "right_eye",
          "x": 379.6150817871094,
          "y": 129.380126953125,
          "confidence": 0.19854967296123505
        },
        {
          "name": "left_ear",
          "x": 391.5611877441406,
          "y": 129.55184936523438,
          "confidence": 0.10268749296665192
        },
        {
          "name": "right_ear",
          "x": 391.9046630859375,
          "y": 131.91970825195312,
          "confidence": 0.1079663410782814
        },
        {
          "name": "left_shoulder",
          "x": 392.76324462890625,
          "y": 125.35787200927734,
          "confidence": 0.029005564749240875
        },
        {
          "name": "right_shoulder",
          "x": 392.1570129394531,
          "y": 134.8314208984375,
          "confidence": 0.05120193585753441
        },
        {
          "name": "left_elbow",
          "x": 383.9020080566406,
          "y": 109.50078582763672,
          "confidence": 0.09010747075080872
        },
        {
          "name": "right_elbow",
          "x": 383.4460144042969,
          "y": 108.85384368896484,
          "confidence": 0.07612262666225433
        },
        {
          "name": "left_wrist",
          "x": 387.46905517578125,
          "y": 129.66140747070312,
          "confidence": 0.09909535944461823
        },
        {
          "name": "right_wrist",
          "x": 380.21832275390625,
          "y": 127.41397857666016,
          "confidence": 0.07563026994466782
        },
        {
          "name": "left_hip",
          "x": 389.8415222167969,
          "y": 126.26605987548828,
          "confidence": 0.038519956171512604
        },
        {
          "name": "right_hip",
          "x": 390.9752197265625,
          "y": 127.0363540649414,
          "confidence": 0.05090591683983803
        },
        {
          "name": "left_knee",
          "x": 383.280517578125,
          "y": 109.8232192993164,
          "confidence": 0.07001779228448868
        },
        {
          "name": "right_knee",
          "x": 383.6602783203125,
          "y": 109.1740951538086,
          "confidence": 0.19581440091133118
        },
        {
          "name": "left_ankle",
          "x": 391.53314208984375,
          "y": 125.76032257080078,
          "confidence": 0.15665116906166077
        },
        {
          "name": "right_ankle",
          "x": 391.262451171875,
          "y": 125.10880279541016,
          "confidence": 0.20144066214561462
        }
      ]
    }
  ],
  "image_width": 0,
  "image_height": 0
}
